{"<PAD>": 0, "<BOS>": 1, "<EOS>": 2, "<UNK>": 3, "，": 4, "的": 5, "。": 6, "一": 7, "是": 8, "不": 9, "在": 10, "人": 11, "有": 12, "民": 13, "到": 14, "這": 15, "台": 16, "來": 17, "大": 18, "會": 19, "生": 20, "上": 21, "中": 22, "了": 23, "要": 24, "為": 25, "國": 26, "出": 27, "年": 28, ",": 29, "過": 30, "十": 31, "新": 32, "個": 33, "以": 34, "家": 35, "就": 36, "車": 37, "後": 38, "成": 39, "時": 40, "他": 41, "我": 42, "灣": 43, "們": 44, "也": 45, "、": 46, "地": 47, "現": 48, "多": 49, "學": 50, "還": 51, "自": 52, "天": 53, "發": 54, "下": 55, "說": 56, "經": 57, "報": 58, "沒": 59, "子": 60, "」": 61, "「": 62, "公": 63, "導": 64, "當": 65, "前": 66, "和": 67, "開": 68, "高": 69, "工": 70, "都": 71, "三": 72, "方": 73, "動": 74, "著": 75, "對": 76, "小": 77, "然": 78, "聞": 79, "視": 80, "可": 81, "面": 82, "心": 83, "被": 84, "日": 85, "水": 86, "二": 87, "用": 88, "得": 89, "政": 90, "行": 91, "看": 92, "本": 93, "能": 94, "市": 95, "因": 96, "進": 97, "好": 98, "外": 99, "法": 100, "讓": 101, "只": 102, "長": 103, "員": 104, "場": 105, "眾": 106, "去": 107, "路": 108, "體": 109, "之": 110, "業": 111, "起": 112, "者": 113, "很": 114, "最": 115, "機": 116, "道": 117, "名": 118, "全": 119, "想": 120, "事": 121, "老": 122, "與": 123, "頭": 124, "麼": 125, "？": 126, "五": 127, "作": 128, "主": 129, "百": 130, "力": 131, "警": 132, "分": 133, "同": 134, "樣": 135, "裡": 136, "位": 137, "加": 138, "所": 139, "些": 140, "運": 141, "無": 142, "月": 143, "意": 144, "重": 145, "南": 146, "兩": 147, "農": 148, "原": 149, "立": 150, "受": 151, "四": 152, "手": 153, "氣": 154, "理": 155, "間": 156, "表": 157, "電": 158, "實": 159, "回": 160, "但": 161, "已": 162, "部": 163, "文": 164, "果": 165, "黨": 166, "化": 167, "從": 168, "；": 169, "社": 170, "價": 171, "定": 172, "萬": 173, "而": 174, "己": 175, "把": 176, "如": 177, "點": 178, "反": 179, "接": 180, "做": 181, "打": 182, "情": 183, "種": 184, "近": 185, "雄": 186, "於": 187, "保": 188, "六": 189, "再": 190, "少": 191, "今": 192, "制": 193, "客": 194, "常": 195, "海": 196, "選": 197, "代": 198, "元": 199, "次": 200, "山": 201, "治": 202, "活": 203, "身": 204, "統": 205, "感": 206, "產": 207, "入": 208, "八": 209, "問": 210, "區": 211, "期": 212, "造": 213, "收": 214, "那": 215, "你": 216, "府": 217, "結": 218, "才": 219, "度": 220, "金": 221, "相": 222, "明": 223, "美": 224, "口": 225, "走": 226, "女": 227, "東": 228, "將": 229, "縣": 230, "認": 231, "火": 232, "幾": 233, "合": 234, "又": 235, "教": 236, "放": 237, "九": 238, "其": 239, "每": 240, "知": 241, "變": 242, "正": 243, "花": 244, "住": 245, "團": 246, "利": 247, "師": 248, "義": 249, "阿": 250, ".": 251, "通": 252, "消": 253, "醫": 254, "關": 255, "應": 256, "內": 257, "及": 258, "品": 259, "提": 260, "安": 261, "直": 262, "院": 263, "權": 264, "量": 265, "議": 266, "卻": 267, "更": 268, "太": 269, "孩": 270, "局": 271, "物": 272, "北": 273, "示": 274, "等": 275, "解": 276, "店": 277, "光": 278, "處": 279, "總": 280, "費": 281, "包": 282, "風": 283, "比": 284, "0": 285, "邊": 286, "建": 287, "資": 288, "調": 289, "吃": 290, "程": 291, "什": 292, "清": 293, "七": 294, "千": 295, "辦": 296, "或": 297, "求": 298, "平": 299, "題": 300, "校": 301, "救": 302, "油": 303, "先": 304, "陳": 305, "像": 306, "特": 307, "給": 308, "向": 309, "錢": 310, "滿": 311, "門": 312, "流": 313, "馬": 314, "男": 315, "除": 316, "難": 317, "林": 318, "真": 319, "觀": 320, "連": 321, "別": 322, "傳": 323, "目": 324, "第": 325, "1": 326, "媽": 327, "使": 328, "！": 329, "單": 330, "她": 331, "許": 332, "隊": 333, "此": 334, "魚": 335, "續": 336, "舉": 337, "望": 338, "強": 339, "數": 340, "失": 341, "往": 342, "拿": 343, "管": 344, "改": 345, "影": 346, "商": 347, "照": 348, "至": 349, "防": 350, "遊": 351, "整": 352, "2": 353, "友": 354, "帶": 355, "件": 356, "案": 357, "性": 358, "賣": 359, "園": 360, "親": 361, "算": 362, "線": 363, "送": 364, "查": 365, "完": 366, "命": 367, "司": 368, "由": 369, "準": 370, "持": 371, "話": 372, "聲": 373, "色": 374, "計": 375, "候": 376, "熱": 377, "護": 378, "死": 379, "環": 380, "抗": 381, "落": 382, "站": 383, "找": 384, "任": 385, "傷": 386, "參": 387, "土": 388, "夠": 389, "英": 390, "始": 391, "跟": 392, "空": 393, "世": 394, "備": 395, "界": 396, "交": 397, "信": 398, "決": 399, "歲": 400, "廠": 401, "勞": 402, "格": 403, "鄉": 404, "姓": 405, "必": 406, "告": 407, "希": 408, "展": 409, "式": 410, "幫": 411, "樂": 412, "需": 413, "神": 414, "轉": 415, "白": 416, "超": 417, "檢": 418, "華": 419, "病": 420, "：": 421, "該": 422, "養": 423, "竟": 424, "軍": 425, "語": 426, "官": 427, "演": 428, "緊": 429, "料": 430, "買": 431, "雖": 432, "引": 433, "務": 434, "基": 435, "設": 436, "西": 437, "派": 438, "早": 439, "群": 440, "張": 441, "底": 442, "嗎": 443, "投": 444, "停": 445, "a": 446, "爭": 447, "勢": 448, "條": 449, "假": 450, "聽": 451, "未": 452, "母": 453, "何": 454, "壓": 455, "票": 456, "兒": 457, "食": 458, "離": 459, "育": 460, "共": 461, "班": 462, "記": 463, "斷": 464, "漲": 465, "非": 466, "服": 467, "趕": 468, "黑": 469, "達": 470, "史": 471, "驗": 472, "專": 473, "晚": 474, "香": 475, "船": 476, "忙": 477, "快": 478, "愛": 479, "助": 480, "見": 481, "集": 482, "取": 483, "龍": 484, "步": 485, "仍": 486, "請": 487, "害": 488, "號": 489, "歷": 490, "根": 491, "便": 492, "片": 493, "漁": 494, "營": 495, "委": 496, "破": 497, "擔": 498, "質": 499, "論": 500, "怎": 501, "樹": 502, "越": 503, "獨": 504, "裝": 505, "士": 506, "察": 507, "支": 508, "訴": 509, "各": 510, "貨": 511, "午": 512, "眼": 513, "紅": 514, "級": 515, "講": 516, "愈": 517, "廟": 518, "書": 519, "遭": 520, "須": 521, "鐵": 522, "且": 523, "疑": 524, "節": 525, "嘉": 526, "黃": 527, "形": 528, "?": 529, "突": 530, "境": 531, "畫": 532, "朋": 533, "輕": 534, "半": 535, "規": 536, "念": 537, "依": 538, "較": 539, "戰": 540, "覺": 541, "雨": 542, "球": 543, "犯": 544, "仔": 545, "排": 546, "批": 547, "菜": 548, "源": 549, "肉": 550, "響": 551, "腳": 552, "考": 553, "嫌": 554, "搶": 555, "屬": 556, "思": 557, "核": 558, "田": 559, "留": 560, "父": 561, "標": 562, "推": 563, "器": 564, "嚴": 565, "毒": 566, "並": 567, "里": 568, "急": 569, "創": 570, "紀": 571, "族": 572, "港": 573, "掉": 574, "協": 575, "石": 576, "益": 577, "剛": 578, "即": 579, "指": 580, "音": 581, "際": 582, "餐": 583, "苦": 584, "習": 585, "網": 586, "繼": 587, "零": 588, "味": 589, "術": 590, "型": 591, "領": 592, "約": 593, "獲": 594, "爆": 595, "李": 596, "樓": 597, "曾": 598, "份": 599, "另": 600, "組": 601, "附": 602, "o": 603, "村": 604, "濟": 605, "證": 606, "屏": 607, "甚": 608, "隨": 609, "顧": 610, "街": 611, "災": 612, "景": 613, "象": 614, "低": 615, "房": 616, "透": 617, "跑": 618, "酒": 619, "豬": 620, "值": 621, "倒": 622, "興": 623, "烏": 624, "i": 625, "功": 626, "願": 627, "夜": 628, "言": 629, "製": 630, "藥": 631, "待": 632, "致": 633, "若": 634, "追": 635, "婦": 636, "聯": 637, "替": 638, "否": 639, "旁": 640, "存": 641, "免": 642, "供": 643, "深": 644, "狀": 645, "痛": 646, "隻": 647, "溫": 648, "舊": 649, "n": 650, "怕": 651, "王": 652, "容": 653, "精": 654, "銷": 655, "撞": 656, "識": 657, "似": 658, "差": 659, "判": 660, "幸": 661, "責": 662, "採": 663, "偷": 664, "登": 665, "修": 666, "確": 667, "木": 668, "歌": 669, "課": 670, "態": 671, "承": 672, "段": 673, "旅": 674, "湖": 675, "科": 676, "館": 677, "獎": 678, "騎": 679, "退": 680, "休": 681, "錄": 682, "戲": 683, "拍": 684, "復": 685, "戶": 686, "具": 687, "靠": 688, "預": 689, "闆": 690, "宣": 691, "星": 692, "換": 693, "補": 694, "稱": 695, "寫": 696, "廢": 697, "輛": 698, "雲": 699, "賽": 700, "技": 701, "字": 702, "刻": 703, "終": 704, "藝": 705, "德": 706, "故": 707, "衝": 708, "控": 709, "減": 710, "禮": 711, "竹": 712, "研": 713, "速": 714, "島": 715, "積": 716, "況": 717, "負": 718, "署": 719, "吸": 720, "福": 721, "首": 722, "布": 723, "飛": 724, "足": 725, "飯": 726, "擊": 727, "e": 728, "冷": 729, "8": 730, "坐": 731, "古": 732, "屋": 733, "初": 734, "駕": 735, "增": 736, "草": 737, "層": 738, "徒": 739, "亡": 740, "職": 741, "階": 742, "款": 743, "雙": 744, "迫": 745, "駛": 746, "玩": 747, "米": 748, "斤": 749, "恐": 750, "圍": 751, "竊": 752, "遇": 753, "叫": 754, "談": 755, "輪": 756, "呼": 757, "喜": 758, "討": 759, "蔡": 760, "(": 761, "險": 762, ")": 763, "配": 764, "鎮": 765, "爸": 766, "謝": 767, "省": 768, "血": 769, "袋": 770, "殖": 771, "維": 772, "拉": 773, "損": 774, "善": 775, "牌": 776, "息": 777, "牛": 778, "困": 779, "穿": 780, "系": 781, "青": 782, "燒": 783, "敢": 784, "拜": 785, "究": 786, "財": 787, "乎": 788, "攤": 789, "罰": 790, "l": 791, "暴": 792, "危": 793, "苗": 794, "錯": 795, "9": 796, "角": 797, "遠": 798, "薪": 799, "移": 800, "讀": 801, "懷": 802, "歡": 803, "瓜": 804, "棄": 805, "類": 806, "河": 807, "壞": 808, "跳": 809, "室": 810, "潮": 811, "注": 812, "慢": 813, "弟": 814, "志": 815, "腦": 816, "淡": 817, "喊": 818, "監": 819, "革": 820, "夫": 821, "降": 822, "廣": 823, "久": 824, "笑": 825, "衛": 826, "週": 827, "3": 828, "執": 829, "居": 830, "據": 831, "順": 832, "陽": 833, "榮": 834, "施": 835, "策": 836, "則": 837, "易": 838, "祖": 839, "評": 840, "板": 841, "左": 842, "茶": 843, "醒": 844, "健": 845, "驚": 846, "括": 847, "蘭": 848, "麵": 849, "購": 850, "優": 851, "巡": 852, "切": 853, "蓋": 854, "翻": 855, "稻": 856, "絕": 857, "賺": 858, "試": 859, "澎": 860, "背": 861, "般": 862, "享": 863, "衣": 864, "販": 865, "殺": 866, "例": 867, "雞": 868, "燈": 869, "療": 870, "童": 871, "避": 872, "僅": 873, "缺": 874, "練": 875, "綠": 876, "5": 877, "升": 878, "限": 879, "喝": 880, "材": 881, "載": 882, "箱": 883, "罪": 884, "顯": 885, "籍": 886, "哪": 887, "洗": 888, "止": 889, "鐘": 890, "宮": 891, "塊": 892, "奇": 893, "捕": 894, "座": 895, "浪": 896, "唱": 897, "庭": 898, "麻": 899, "洲": 900, "堅": 901, "染": 902, "宜": 903, "效": 904, "彈": 905, "貼": 906, "搭": 907, "紙": 908, "怪": 909, "簡": 910, "h": 911, "藉": 912, "粉": 913, "陣": 914, "患": 915, "皮": 916, "蛋": 917, "付": 918, "A": 919, "媒": 920, "冰": 921, "良": 922, "踏": 923, "列": 924, "亂": 925, "周": 926, "卡": 927, "置": 928, "紛": 929, "架": 930, "抓": 931, "春": 932, "乾": 933, "圖": 934, "溪": 935, "禍": 936, "6": 937, "率": 938, "C": 939, "印": 940, "援": 941, "畢": 942, "隔": 943, "威": 944, "嚇": 945, "武": 946, "違": 947, "誤": 948, "玉": 949, "障": 950, "堆": 951, "右": 952, "庫": 953, "臨": 954, "令": 955, "充": 956, "桌": 957, "模": 958, "招": 959, "捐": 960, "逃": 961, "拆": 962, "極": 963, "束": 964, "騙": 965, "舞": 966, "佈": 967, "扁": 968, "項": 969, "掌": 970, "貴": 971, "航": 972, "轎": 973, "震": 974, "銀": 975, "呢": 976, "吳": 977, "鳳": 978, "楚": 979, "旗": 980, "筆": 981, "嬤": 982, "釋": 983, "葉": 984, "細": 985, "兵": 986, "蜂": 987, "季": 988, "尺": 989, "彩": 990, "席": 991, "涉": 992, "億": 993, "岸": 994, "慶": 995, "豆": 996, "野": 997, "劇": 998, "針": 999, "蘇": 1000, "洋": 1001, "橋": 1002, "城": 1003, "係": 1004, "鬧": 1005, "迷": 1006, "短": 1007, "波": 1008, "韓": 1009, "糖": 1010, "u": 1011, "污": 1012, "掛": 1013, "散": 1014, "射": 1015, "申": 1016, "誰": 1017, "構": 1018, "賠": 1019, "抱": 1020, "鼓": 1021, "尊": 1022, "康": 1023, "捷": 1024, "互": 1025, "忍": 1026, "彰": 1027, "訪": 1028, "鮮": 1029, "亞": 1030, "瓦": 1031, "搬": 1032, "頂": 1033, "擇": 1034, "麗": 1035, "昨": 1036, "尾": 1037, "g": 1038, "…": 1039, "疫": 1040, "颱": 1041, "賞": 1042, "盛": 1043, "聚": 1044, "鬥": 1045, "槍": 1046, "遺": 1047, "s": 1048, "織": 1049, "臉": 1050, "烈": 1051, "r": 1052, "稅": 1053, "挑": 1054, "剩": 1055, "盡": 1056, "適": 1057, "廳": 1058, "妻": 1059, "簽": 1060, "延": 1061, "律": 1062, "尋": 1063, "償": 1064, "累": 1065, "丟": 1066, "4": 1067, "訓": 1068, "富": 1069, "賴": 1070, "守": 1071, "惡": 1072, "冬": 1073, "陸": 1074, "咖": 1075, "姐": 1076, "沙": 1077, "睡": 1078, "顆": 1079, "冒": 1080, "估": 1081, "煙": 1082, "濃": 1083, "私": 1084, "測": 1085, "婚": 1086, "售": 1087, "郵": 1088, "罵": 1089, "蓮": 1090, "弱": 1091, "曲": 1092, "佔": 1093, "脫": 1094, "盤": 1095, "毀": 1096, "寶": 1097, "握": 1098, "績": 1099, "宅": 1100, "牆": 1101, "寒": 1102, "狗": 1103, "炸": 1104, "熟": 1105, "禁": 1106, "訊": 1107, "博": 1108, "堂": 1109, "伯": 1110, "沿": 1111, "碼": 1112, "築": 1113, "毛": 1114, "索": 1115, "飲": 1116, "y": 1117, "封": 1118, "藏": 1119, "甲": 1120, "慘": 1121, "覽": 1122, "T": 1123, "激": 1124, "靜": 1125, "豐": 1126, "兄": 1127, "永": 1128, "歉": 1129, "幕": 1130, "徵": 1131, "介": 1132, "操": 1133, "暖": 1134, "答": 1135, "密": 1136, "溝": 1137, "O": 1138, "審": 1139, "漸": 1140, "辛": 1141, "額": 1142, "埔": 1143, "侵": 1144, "怨": 1145, "拖": 1146, "晨": 1147, "訂": 1148, "砲": 1149, "啡": 1150, "繳": 1151, "舍": 1152, "套": 1153, "倍": 1154, "典": 1155, "鍋": 1156, "龜": 1157, "汽": 1158, "範": 1159, "含": 1160, "泡": 1161, "撿": 1162, "垃": 1163, "圾": 1164, "勇": 1165, "籲": 1166, "裏": 1167, "植": 1168, "努": 1169, "雜": 1170, "刺": 1171, "副": 1172, "症": 1173, "t": 1174, "刑": 1175, "邀": 1176, "阻": 1177, "輝": 1178, "湯": 1179, "胡": 1180, "忘": 1181, "距": 1182, "既": 1183, "泥": 1184, "奶": 1185, "陪": 1186, "劃": 1187, "冠": 1188, "奪": 1189, "k": 1190, "擋": 1191, "嬰": 1192, "逮": 1193, "噴": 1194, "敗": 1195, "吊": 1196, "診": 1197, "虎": 1198, "詐": 1199, "池": 1200, "拒": 1201, "企": 1202, "甜": 1203, "鎖": 1204, "塑": 1205, "m": 1206, "途": 1207, "─": 1208, "刀": 1209, "7": 1210, "輸": 1211, "抵": 1212, "歹": 1213, "戴": 1214, "P": 1215, "仁": 1216, "滅": 1217, "\"": 1218, "迎": 1219, "擺": 1220, "菊": 1221, "孫": 1222, "哥": 1223, "召": 1224, "M": 1225, "S": 1226, "江": 1227, "亮": 1228, "煮": 1229, "擠": 1230, "慮": 1231, "趁": 1232, "牽": 1233, "鳥": 1234, "游": 1235, "劉": 1236, "靈": 1237, "偏": 1238, "丁": 1239, "鴨": 1240, "剝": 1241, "素": 1242, "租": 1243, "抽": 1244, "翁": 1245, "固": 1246, "梨": 1247, "幹": 1248, "佳": 1249, "悲": 1250, "熊": 1251, "普": 1252, "鄭": 1253, "洞": 1254, "爬": 1255, "儘": 1256, "番": 1257, "聖": 1258, "盜": 1259, "猴": 1260, "懂": 1261, "硬": 1262, "斯": 1263, "壁": 1264, "授": 1265, "隆": 1266, "哭": 1267, "棒": 1268, "穩": 1269, "乘": 1270, "域": 1271, "鄰": 1272, "蜜": 1273, "!": 1274, "楊": 1275, "慣": 1276, "爐": 1277, "伴": 1278, "嘴": 1279, "宿": 1280, "趣": 1281, "娘": 1282, "均": 1283, "櫃": 1284, "它": 1285, "勝": 1286, "夢": 1287, "謂": 1288, "闖": 1289, "輩": 1290, "憶": 1291, "漏": 1292, "蚵": 1293, "鋼": 1294, "盟": 1295, "裂": 1296, "鞋": 1297, "妹": 1298, "露": 1299, "啟": 1300, "餅": 1301, "搖": 1302, "折": 1303, "圓": 1304, "憤": 1305, "挖": 1306, "揮": 1307, "惠": 1308, "秋": 1309, "癌": 1310, "骨": 1311, "蹟": 1312, "礙": 1313, "觸": 1314, "E": 1315, "秀": 1316, "）": 1317, "跌": 1318, "肥": 1319, "暫": 1320, "搜": 1321, "桶": 1322, "鹽": 1323, "甘": 1324, "句": 1325, "搞": 1326, "洪": 1327, "遍": 1328, "智": 1329, "遷": 1330, "泰": 1331, "競": 1332, "駐": 1333, "裁": 1334, "奈": 1335, "桃": 1336, "怒": 1337, "緩": 1338, "凌": 1339, "（": 1340, "豪": 1341, "爛": 1342, "忠": 1343, "峰": 1344, "巴": 1345, "吹": 1346, "奴": 1347, "股": 1348, "歐": 1349, "縮": 1350, "符": 1351, "鬼": 1352, "擁": 1353, "B": 1354, "陷": 1355, "殼": 1356, "祝": 1357, "渡": 1358, "煩": 1359, "逐": 1360, "氛": 1361, "偵": 1362, "勵": 1363, "編": 1364, "疏": 1365, "幼": 1366, "郭": 1367, "蟲": 1368, "茄": 1369, "栽": 1370, "炒": 1371, "獻": 1372, "賊": 1373, "G": 1374, "督": 1375, "攝": 1376, "央": 1377, "劑": 1378, "耳": 1379, "帳": 1380, "異": 1381, "窗": 1382, "吧": 1383, "削": 1384, "欣": 1385, "夏": 1386, "幣": 1387, "播": 1388, "序": 1389, "欺": 1390, "雪": 1391, "昏": 1392, "殘": 1393, "克": 1394, "拔": 1395, "賭": 1396, "歸": 1397, "栗": 1398, "珍": 1399, "按": 1400, "炎": 1401, "床": 1402, "棟": 1403, "恢": 1404, "《": 1405, "蕉": 1406, "淚": 1407, "蹤": 1408, "寄": 1409, "跡": 1410, "F": 1411, "帽": 1412, "》": 1413, "綁": 1414, "暑": 1415, "艇": 1416, "憂": 1417, "培": 1418, "霸": 1419, "寮": 1420, "飽": 1421, "朝": 1422, "貿": 1423, "返": 1424, "攻": 1425, "伍": 1426, "聊": 1427, "巷": 1428, "碗": 1429, "贈": 1430, "微": 1431, "贏": 1432, "混": 1433, "d": 1434, "燃": 1435, "厝": 1436, "滾": 1437, "灌": 1438, "榕": 1439, "仙": 1440, "梯": 1441, "蔣": 1442, "緒": 1443, "芒": 1444, "募": 1445, "拚": 1446, "宴": 1447, "版": 1448, "尚": 1449, "肯": 1450, "探": 1451, "沉": 1452, "髮": 1453, "椅": 1454, "鬆": 1455, "礎": 1456, "D": 1457, "尤": 1458, "盾": 1459, "閒": 1460, "炮": 1461, "圈": 1462, "b": 1463, "宇": 1464, "耕": 1465, "遲": 1466, "拼": 1467, "啊": 1468, "膠": 1469, "鹿": 1470, "隸": 1471, "婆": 1472, "蚊": 1473, "押": 1474, "藍": 1475, "N": 1476, "絲": 1477, "賓": 1478, "偶": 1479, "割": 1480, "玻": 1481, "枝": 1482, "鏡": 1483, "扣": 1484, "京": 1485, "飾": 1486, "純": 1487, "璃": 1488, "端": 1489, "雷": 1490, "c": 1491, "詞": 1492, "酸": 1493, "巨": 1494, "腐": 1495, "儀": 1496, "唯": 1497, "釣": 1498, "擾": 1499, "撐": 1500, "章": 1501, "滋": 1502, "借": 1503, "勤": 1504, "掩": 1505, "繞": 1506, "債": 1507, "爺": 1508, "旦": 1509, "插": 1510, "瓶": 1511, "躲": 1512, "津": 1513, ";": 1514, "添": 1515, "哲": 1516, "幅": 1517, "詢": 1518, "胎": 1519, "誠": 1520, "巧": 1521, "洩": 1522, "牧": 1523, "揚": 1524, "州": 1525, "託": 1526, "閃": 1527, "欠": 1528, "凍": 1529, "沖": 1530, "軟": 1531, "貧": 1532, "憲": 1533, "川": 1534, "促": 1535, "述": 1536, "壇": 1537, "柴": 1538, "砍": 1539, "戒": 1540, "寬": 1541, "祭": 1542, "納": 1543, "逼": 1544, "噸": 1545, "莊": 1546, "斑": 1547, "H": 1548, "閉": 1549, "頻": 1550, "剪": 1551, "絡": 1552, "舒": 1553, "矛": 1554, "僚": 1555, "餘": 1556, "擴": 1557, "邏": 1558, "覆": 1559, "肚": 1560, "狂": 1561, "蔬": 1562, "嘆": 1563, "埋": 1564, "淹": 1565, "偽": 1566, "膽": 1567, "乳": 1568, "曬": 1569, "忽": 1570, "脆": 1571, "咬": 1572, "扶": 1573, "艘": 1574, "牙": 1575, "兇": 1576, "坡": 1577, "叔": 1578, "概": 1579, "坪": 1580, "松": 1581, "羅": 1582, "暗": 1583, "俊": 1584, "掃": 1585, "銅": 1586, "惜": 1587, "潔": 1588, "壽": 1589, "飆": 1590, "繁": 1591, "融": 1592, "昌": 1593, "役": 1594, "默": 1595, "末": 1596, "慈": 1597, "廖": 1598, "荷": 1599, "K": 1600, "軌": 1601, "碰": 1602, "祈": 1603, "某": 1604, "昇": 1605, "捲": 1606, "串": 1607, "曆": 1608, "肇": 1609, "塞": 1610, "貓": 1611, "弄": 1612, "輔": 1613, "荒": 1614, "崩": 1615, "擦": 1616, "秘": 1617, "券": 1618, "奉": 1619, "摩": 1620, "涼": 1621, "吵": 1622, "漂": 1623, "貪": 1624, "敏": 1625, "勸": 1626, "浮": 1627, "烤": 1628, "臭": 1629, ":": 1630, "惱": 1631, "嗆": 1632, "倉": 1633, "慰": 1634, "鴻": 1635, "L": 1636, "虛": 1637, "閱": 1638, "董": 1639, "Ｏ": 1640, "齡": 1641, "罹": 1642, "雕": 1643, "托": 1644, "虱": 1645, "跨": 1646, "伸": 1647, "梅": 1648, "R": 1649, "顏": 1650, "泳": 1651, "煎": 1652, "妳": 1653, "籌": 1654, "菸": 1655, "厚": 1656, "摔": 1657, "鈔": 1658, "%": 1659, "棵": 1660, "勁": 1661, "后": 1662, "牠": 1663, "滑": 1664, "緝": 1665, "粗": 1666, "牲": 1667, "怖": 1668, "俗": 1669, "讚": 1670, "丹": 1671, "輻": 1672, "宗": 1673, "傾": 1674, "疼": 1675, "灰": 1676, "頃": 1677, "誇": 1678, "棗": 1679, "毫": 1680, "略": 1681, "捨": 1682, "廚": 1683, "獄": 1684, "桿": 1685, "爽": 1686, "鰻": 1687, "奮": 1688, "盼": 1689, "辯": 1690, "珠": 1691, "堪": 1692, "吐": 1693, "雇": 1694, "哀": 1695, "攔": 1696, "漢": 1697, "駁": 1698, "摸": 1699, "撲": 1700, "潛": 1701, "柏": 1702, "挺": 1703, "殊": 1704, "誌": 1705, "穀": 1706, "焚": 1707, "恆": 1708, "驅": 1709, "橫": 1710, "襲": 1711, "疾": 1712, "脅": 1713, "遣": 1714, "腸": 1715, "鼠": 1716, "誕": 1717, "齊": 1718, "薑": 1719, "庄": 1720, "乏": 1721, "帆": 1722, "啦": 1723, "粽": 1724, "撫": 1725, "諾": 1726, "犧": 1727, "焦": 1728, "琴": 1729, "徹": 1730, "鼻": 1731, "墾": 1732, "筋": 1733, "朵": 1734, "碎": 1735, "澄": 1736, "趨": 1737, "扭": 1738, "斗": 1739, "猛": 1740, "獼": 1741, "麥": 1742, "汁": 1743, "妥": 1744, "映": 1745, "砂": 1746, "瑞": 1747, "淑": 1748, "腿": 1749, "坑": 1750, "霧": 1751, "斃": 1752, "撈": 1753, "蔥": 1754, "罩": 1755, "痕": 1756, "p": 1757, "罕": 1758, "帝": 1759, "糟": 1760, "傅": 1761, "伏": 1762, "吞": 1763, "柯": 1764, "隱": 1765, "踐": 1766, "貢": 1767, "汗": 1768, "尿": 1769, "旺": 1770, "詹": 1771, "孔": 1772, "仰": 1773, "廂": 1774, "糕": 1775, "措": 1776, "尖": 1777, "樺": 1778, "撤": 1779, "糾": 1780, "倫": 1781, "腰": 1782, "鞭": 1783, "犬": 1784, "棉": 1785, "鑽": 1786, "贓": 1787, "摘": 1788, "銘": 1789, "煞": 1790, "躺": 1791, "趟": 1792, "漆": 1793, "燕": 1794, "兼": 1795, "複": 1796, "罐": 1797, "壯": 1798, "廷": 1799, "濕": 1800, "夾": 1801, "羊": 1802, "瘦": 1803, "泉": 1804, "循": 1805, "嶼": 1806, "螺": 1807, "劫": 1808, "杯": 1809, "冊": 1810, "緣": 1811, "拾": 1812, "睛": 1813, "譜": 1814, "蒸": 1815, "嚐": 1816, "坦": 1817, "逆": 1818, "彎": 1819, "傍": 1820, "扮": 1821, "併": 1822, "鋒": 1823, "涵": 1824, "逸": 1825, "騰": 1826, "獅": 1827, "填": 1828, "筍": 1829, "恩": 1830, "敬": 1831, "綜": 1832, "貌": 1833, "孝": 1834, "喪": 1835, "臟": 1836, "慎": 1837, "奔": 1838, "蝦": 1839, "紫": 1840, "飼": 1841, "徐": 1842, "敲": 1843, "踩": 1844, "纜": 1845, "拳": 1846, "柱": 1847, "遮": 1848, "尼": 1849, "褲": 1850, "淨": 1851, "耐": 1852, "漫": 1853, "逛": 1854, "佛": 1855, "丈": 1856, "滴": 1857, "〈": 1858, "〉": 1859, "孕": 1860, "淋": 1861, "氧": 1862, "屆": 1863, "刊": 1864, "扯": 1865, "悉": 1866, "碳": 1867, "唸": 1868, "廁": 1869, "盒": 1870, "吉": 1871, "敦": 1872, "稀": 1873, "樟": 1874, "灘": 1875, "宏": 1876, "卸": 1877, "貞": 1878, "乖": 1879, "雅": 1880, "飄": 1881, "眠": 1882, "屍": 1883, "森": 1884, "莓": 1885, "縱": 1886, "夕": 1887, "耗": 1888, "鍵": 1889, "繩": 1890, "傻": 1891, "鹹": 1892, "契": 1893, "磚": 1894, "紹": 1895, "灑": 1896, "諷": 1897, "燙": 1898, "辱": 1899, "沈": 1900, "惹": 1901, "籠": 1902, "陰": 1903, "井": 1904, "液": 1905, "逝": 1906, "濱": 1907, "欲": 1908, "悶": 1909, "繪": 1910, "艦": 1911, "迴": 1912, "牡": 1913, "械": 1914, "櫻": 1915, "貸": 1916, "譽": 1917, "樑": 1918, "辨": 1919, "呈": 1920, "遵": 1921, "潭": 1922, "鷺": 1923, "罷": 1924, "巢": 1925, "刮": 1926, "頓": 1927, "膚": 1928, "稍": 1929, "泛": 1930, "窮": 1931, "髒": 1932, "腎": 1933, "鋪": 1934, "酥": 1935, "孤": 1936, "縫": 1937, "宰": 1938, "屠": 1939, "芬": 1940, "姊": 1941, "艱": 1942, "寧": 1943, "醉": 1944, "腹": 1945, "冤": 1946, "屈": 1947, "糊": 1948, "淺": 1949, "碑": 1950, "椒": 1951, "禽": 1952, "谷": 1953, "魂": 1954, "蟹": 1955, "妙": 1956, "醬": 1957, "籃": 1958, "珊": 1959, "貝": 1960, "祥": 1961, "塗": 1962, "俱": 1963, "肺": 1964, "莫": 1965, "湧": 1966, "刷": 1967, "檳": 1968, "檔": 1969, "敵": 1970, "瞭": 1971, "篇": 1972, "跪": 1973, "琉": 1974, "澡": 1975, "奧": 1976, "胸": 1977, "疊": 1978, "勘": 1979, "芭": 1980, "餵": 1981, "姨": 1982, "溺": 1983, "瞬": 1984, "潤": 1985, "鞏": 1986, "抬": 1987, "贊": 1988, "余": 1989, "析": 1990, "胃": 1991, "鬱": 1992, "偉": 1993, "賢": 1994, "榔": 1995, "鵝": 1996, "糧": 1997, "蝶": 1998, "予": 1999, "斥": 2000, "傘": 2001, "肝": 2002, "辣": 2003, "捉": 2004, "肖": 2005, "睜": 2006, "慌": 2007, "菇": 2008, "唐": 2009, "塌": 2010, "芝": 2011, "鍾": 2012, "w": 2013, "衡": 2014, "曝": 2015, "攜": 2016, "虧": 2017, "傑": 2018, "脈": 2019, "占": 2020, "衰": 2021, "遶": 2022, "肩": 2023, "桐": 2024, "隧": 2025, "喘": 2026, "勒": 2027, "斜": 2028, "榨": 2029, "稚": 2030, "囡": 2031, "勾": 2032, "塔": 2033, "皇": 2034, "揭": 2035, "鷹": 2036, "寺": 2037, "澳": 2038, "蛇": 2039, "堤": 2040, "竄": 2041, "漿": 2042, "嘗": 2043, "謊": 2044, "柚": 2045, "陶": 2046, "蒐": 2047, "諒": 2048, "Y": 2049, "紋": 2050, "彼": 2051, "柳": 2052, "枯": 2053, "蕭": 2054, "亭": 2055, "慧": 2056, "悠": 2057, "廉": 2058, "棚": 2059, "遙": 2060, "紗": 2061, "仲": 2062, "牢": 2063, "薯": 2064, "嬸": 2065, "拋": 2066, "柑": 2067, "仿": 2068, "蹈": 2069, "腫": 2070, "闢": 2071, "秒": 2072, "憑": 2073, "址": 2074, "窩": 2075, "鱷": 2076, "蒜": 2077, "塭": 2078, "欄": 2079, "瑚": 2080, "鮪": 2081, "羈": 2082, "君": 2083, "誘": 2084, "輯": 2085, "譯": 2086, "轟": 2087, "哈": 2088, "朱": 2089, "—": 2090, "懼": 2091, "陌": 2092, "虐": 2093, "浴": 2094, "瘋": 2095, "晃": 2096, "魯": 2097, "蘿": 2098, "蔔": 2099, "奸": 2100, "捍": 2101, "毆": 2102, "堵": 2103, "I": 2104, "鑑": 2105, "憾": 2106, "銳": 2107, "旋": 2108, "擬": 2109, "辜": 2110, "丸": 2111, "茂": 2112, "匪": 2113, "遞": 2114, "姿": 2115, "慨": 2116, "乩": 2117, "粒": 2118, "悔": 2119, "儲": 2120, "薄": 2121, "准": 2122, "晶": 2123, "．": 2124, "劍": 2125, "胞": 2126, "聘": 2127, "截": 2128, "捧": 2129, "翔": 2130, "您": 2131, "鍊": 2132, "踢": 2133, "磨": 2134, "夥": 2135, "秩": 2136, "嶺": 2137, "琵": 2138, "姑": 2139, "暈": 2140, "盆": 2141, "趴": 2142, "塵": 2143, "炭": 2144, "娶": 2145, "蓄": 2146, "妨": 2147, "脂": 2148, "賄": 2149, "螢": 2150, "肢": 2151, "扛": 2152, "躍": 2153, "錦": 2154, "菌": 2155, "側": 2156, "溉": 2157, "逢": 2158, "熬": 2159, "狼": 2160, "翼": 2161, "壟": 2162, "崇": 2163, "裕": 2164, "詩": 2165, "傲": 2166, "耶": 2167, "拓": 2168, "描": 2169, "喚": 2170, "菲": 2171, "癱": 2172, "獵": 2173, "囂": 2174, "檯": 2175, "嘛": 2176, "耀": 2177, "轄": 2178, "凱": 2179, "悄": 2180, "催": 2181, "莉": 2182, "沾": 2183, "徑": 2184, "筒": 2185, "釐": 2186, "挨": 2187, "皆": 2188, "攪": 2189, "葬": 2190, "墓": 2191, "闊": 2192, "卵": 2193, "澱": 2194, "臂": 2195, "攀": 2196, "締": 2197, "洛": 2198, "註": 2199, "聰": 2200, "杜": 2201, "辭": 2202, "氏": 2203, "猶": 2204, "繫": 2205, "墜": 2206, "釀": 2207, "屯": 2208, "勉": 2209, "椰": 2210, "辰": 2211, "滷": 2212, "碌": 2213, "振": 2214, "耍": 2215, "喔": 2216, "昭": 2217, "呆": 2218, "爾": 2219, "邁": 2220, "撼": 2221, "昂": 2222, "訝": 2223, "煌": 2224, "干": 2225, "秧": 2226, "彷": 2227, "舌": 2228, "嫁": 2229, "蒼": 2230, "猩": 2231, "擱": 2232, "弊": 2233, "竭": 2234, "袖": 2235, "崑": 2236, "龐": 2237, "艷": 2238, "緻": 2239, "熄": 2240, "獸": 2241, "旱": 2242, "彿": 2243, "潘": 2244, "擎": 2245, "砸": 2246, "蟻": 2247, "卒": 2248, "謀": 2249, "郎": 2250, "頒": 2251, "閣": 2252, "巾": 2253, "倩": 2254, "圳": 2255, "宵": 2256, "邱": 2257, "倆": 2258, "掏": 2259, "蛙": 2260, "蔗": 2261, "鴿": 2262, "颼": 2263, "淪": 2264, "抹": 2265, "婷": 2266, "凝": 2267, "貫": 2268, "U": 2269, "殿": 2270, "艙": 2271, "箭": 2272, "厲": 2273, "黏": 2274, "叛": 2275, "蹲": 2276, "擲": 2277, "盲": 2278, "縛": 2279, "幻": 2280, "摺": 2281, "蠅": 2282, "呂": 2283, "稿": 2284, "W": 2285, "峽": 2286, "錫": 2287, "紮": 2288, "肌": 2289, "V": 2290, "槽": 2291, "燥": 2292, "荔": 2293, "佑": 2294, "潑": 2295, "劣": 2296, "赤": 2297, "墊": 2298, "枋": 2299, "椪": 2300, "丘": 2301, "懸": 2302, "纏": 2303, "邦": 2304, "醜": 2305, "腔": 2306, "頸": 2307, "膀": 2308, "攏": 2309, "饋": 2310, "淤": 2311, "昆": 2312, "橡": 2313, "蝴": 2314, "溼": 2315, "剖": 2316, "凶": 2317, "噪": 2318, "舖": 2319, "崎": 2320, "酪": 2321, "啤": 2322, "桑": 2323, "稽": 2324, "碾": 2325, "濫": 2326, "兆": 2327, "諸": 2328, "幟": 2329, "蒙": 2330, "訟": 2331, "凡": 2332, "澤": 2333, "雀": 2334, "毅": 2335, "梗": 2336, "臥": 2337, "恨": 2338, "胖": 2339, "盧": 2340, "肅": 2341, "彥": 2342, "賤": 2343, "釘": 2344, "仗": 2345, "佩": 2346, "膏": 2347, "迅": 2348, "浩": 2349, "盃": 2350, "庇": 2351, "隍": 2352, "蝠": 2353, "騷": 2354, "庚": 2355, "慕": 2356, "眷": 2357, "菁": 2358, "壤": 2359, "翠": 2360, "酷": 2361, "僑": 2362, "扇": 2363, "歧": 2364, "愚": 2365, "灼": 2366, "鉛": 2367, "畜": 2368, "彌": 2369, "株": 2370, "埕": 2371, "叢": 2372, "媳": 2373, "梁": 2374, "寓": 2375, "礦": 2376, "逗": 2377, "蕩": 2378, "葡": 2379, "萄": 2380, "函": 2381, "挽": 2382, "裹": 2383, "鶯": 2384, "允": 2385, "薦": 2386, "詳": 2387, "殃": 2388, "扎": 2389, "柵": 2390, "匯": 2391, "卷": 2392, "蠻": 2393, "妝": 2394, "礁": 2395, "宛": 2396, "勃": 2397, "剌": 2398, "溜": 2399, "筊": 2400, "粿": 2401, "抄": 2402, "鳴": 2403, "宋": 2404, "雹": 2405, "玫": 2406, "誓": 2407, "拘": 2408, "v": 2409, "凸": 2410, "驕": 2411, "撕": 2412, "亦": 2413, "奏": 2414, "垂": 2415, "衫": 2416, "秤": 2417, "紡": 2418, "霜": 2419, "妄": 2420, "楣": 2421, "烘": 2422, "羨": 2423, "糞": 2424, "滯": 2425, "渣": 2426, "甸": 2427, "拌": 2428, "溢": 2429, "剷": 2430, "茉": 2431, "酵": 2432, "蘋": 2433, "戀": 2434, "瑰": 2435, "赴": 2436, "玲": 2437, "戚": 2438, "廈": 2439, "讞": 2440, "湊": 2441, "銬": 2442, "歇": 2443, "孟": 2444, "鑼": 2445, "輾": 2446, "暢": 2447, "斌": 2448, "猝": 2449, "f": 2450, "碩": 2451, "崙": 2452, "潰": 2453, "伙": 2454, "侮": 2455, "忌": 2456, "枉": 2457, "羞": 2458, "寵": 2459, "餓": 2460, "瑪": 2461, "涯": 2462, "吼": 2463, "郝": 2464, "籤": 2465, "窯": 2466, "嘲": 2467, "兌": 2468, "蛤": 2469, "僱": 2470, "淇": 2471, "壹": 2472, "餡": 2473, "凹": 2474, "哩": 2475, "蝙": 2476, "軋": 2477, "郁": 2478, "玄": 2479, "薛": 2480, "悅": 2481, "燭": 2482, "悼": 2483, "畏": 2484, "馨": 2485, "鈴": 2486, "敷": 2487, "屑": 2488, "仇": 2489, "曉": 2490, "卦": 2491, "毯": 2492, "匙": 2493, "瞧": 2494, "魔": 2495, "恥": 2496, "舟": 2497, "魅": 2498, "梓": 2499, "娃": 2500, "朴": 2501, "禱": 2502, "喇": 2503, "笨": 2504, "鄒": 2505, "鋁": 2506, "錨": 2507, "贖": 2508, "舅": 2509, "蝕": 2510, "妮": 2511, "芽": 2512, "杖": 2513, "葵": 2514, "憐": 2515, "顛": 2516, "琪": 2517, "癮": 2518, "疲": 2519, "餿": 2520, "朗": 2521, "棍": 2522, "諧": 2523, "惶": 2524, "詮": 2525, "掀": 2526, "抖": 2527, "碧": 2528, "琳": 2529, "岡": 2530, "沸": 2531, "泣": 2532, "晴": 2533, "謠": 2534, "懶": 2535, "柔": 2536, "鵬": 2537, "昧": 2538, "瘓": 2539, "螃": 2540, "醇": 2541, "蒂": 2542, "齒": 2543, "橄": 2544, "豎": 2545, "堡": 2546, "綱": 2547, "杉": 2548, "寸": 2549, "紐": 2550, "脹": 2551, "撥": 2552, "乞": 2553, "睹": 2554, "伐": 2555, "覓": 2556, "欽": 2557, "滲": 2558, "懲": 2559, "浸": 2560, "窄": 2561, "潢": 2562, "屢": 2563, "蠣": 2564, "厭": 2565, "兮": 2566, "蠢": 2567, "僻": 2568, "酬": 2569, "漠": 2570, "盈": 2571, "穗": 2572, "兔": 2573, "囤": 2574, "沼": 2575, "羹": 2576, "刨": 2577, "謬": 2578, "祀": 2579, "魠": 2580, "X": 2581, "鱉": 2582, "欖": 2583, "棋": 2584, "賜": 2585, "柿": 2586, "濤": 2587, "矚": 2588, "樸": 2589, "晉": 2590, "狹": 2591, "咒": 2592, "淵": 2593, "卑": 2594, "翅": 2595, "夯": 2596, "芋": 2597, "猜": 2598, "粱": 2599, "坍": 2600, "燉": 2601, "痺": 2602, "炳": 2603, "煉": 2604, "脖": 2605, "蘆": 2606, "茫": 2607, "岩": 2608, "鷗": 2609, "膜": 2610, "烹": 2611, "屁": 2612, "繡": 2613, "竿": 2614, "樁": 2615, "瀉": 2616, "齣": 2617, "擅": 2618, "肪": 2619, "誼": 2620, "姚": 2621, "嘯": 2622, "x": 2623, "撒": 2624, "濁": 2625, "椎": 2626, "裙": 2627, "綿": 2628, "狠": 2629, "愁": 2630, "捏": 2631, "繃": 2632, "躁": 2633, "攬": 2634, "誡": 2635, "伊": 2636, "囚": 2637, "螞": 2638, "煥": 2639, "汙": 2640, "阮": 2641, "茭": 2642, "篩": 2643, "慾": 2644, "蕃": 2645, "菱": 2646, "苳": 2647, "蹋": 2648, "ê": 2649, "侯": 2650, "乙": 2651, "悸": 2652, "羽": 2653, "祕": 2654, "惑": 2655, "叮": 2656, "甩": 2657, "廊": 2658, "驛": 2659, "溶": 2660, "掙": 2661, "娜": 2662, "划": 2663, "頁": 2664, "帥": 2665, "鑾": 2666, "榜": 2667, "錶": 2668, "棲": 2669, "嫩": 2670, "踴": 2671, "愉": 2672, "鼎": 2673, "叭": 2674, "鉤": 2675, "鋸": 2676, "蛛": 2677, "歪": 2678, "曠": 2679, "栩": 2680, "藕": 2681, "耙": 2682, "『": 2683, "』": 2684, "沫": 2685, "鞠": 2686, "躬": 2687, "恰": 2688, "勿": 2689, "Q": 2690, "戳": 2691, "昔": 2692, "幽": 2693, "瞞": 2694, "弘": 2695, "絞": 2696, "譴": 2697, "矮": 2698, "蔽": 2699, "諜": 2700, "敘": 2701, "哄": 2702, "履": 2703, "蓉": 2704, "襄": 2705, "蔭": 2706, "澆": 2707, "渴": 2708, "糯": 2709, "瑯": 2710, "淫": 2711, "擄": 2712, "崗": 2713, "謹": 2714, "隙": 2715, "蜘": 2716, "匠": 2717, "崁": 2718, "阱": 2719, "瀕": 2720, "膩": 2721, "鱔": 2722, "饅": 2723, "魄": 2724, "佬": 2725, "蕙": 2726, "喧": 2727, "蔓": 2728, "噁": 2729, "楷": 2730, "穎": 2731, "撰": 2732, "z": 2733, "芳": 2734, "皂": 2735, "盪": 2736, "瘤": 2737, "鏈": 2738, "豈": 2739, "簾": 2740, "聆": 2741, "痴": 2742, "墨": 2743, "昱": 2744, "鴉": 2745, "桂": 2746, "梭": 2747, "筏": 2748, "巒": 2749, "垮": 2750, "征": 2751, "寢": 2752, "爪": 2753, "覬": 2754, "覦": 2755, "鏽": 2756, "楠": 2757, "鑰": 2758, "麟": 2759, "莒": 2760, "纖": 2761, "魏": 2762, "砷": 2763, "埤": 2764, "蠵": 2765, "笈": 2766, "屎": 2767, "紓": 2768, "虹": 2769, "拐": 2770, "匿": 2771, "俄": 2772, "衷": 2773, "旭": 2774, "霹": 2775, "僵": 2776, "頗": 2777, "祠": 2778, "洽": 2779, "盯": 2780, "霞": 2781, "瀾": 2782, "蓬": 2783, "殉": 2784, "糙": 2785, "挫": 2786, "翹": 2787, "磁": 2788, "脊": 2789, "摧": 2790, "臣": 2791, "瓷": 2792, "靶": 2793, "霖": 2794, "俐": 2795, "祐": 2796, "裸": 2797, "弼": 2798, "鏟": 2799, "黎": 2800, "耘": 2801, "繕": 2802, "氯": 2803, "椿": 2804, "畸": 2805, "蛆": 2806, "穴": 2807, "鏢": 2808, "娛": 2809, "娥": 2810, "范": 2811, "逾": 2812, "披": 2813, "碟": 2814, "瑩": 2815, "眶": 2816, "泄": 2817, "腺": 2818, "旬": 2819, "兜": 2820, "顫": 2821, "鄙": 2822, "揹": 2823, "嘻": 2824, "掘": 2825, "瓊": 2826, "坤": 2827, "豔": 2828, "夭": 2829, "塘": 2830, "誦": 2831, "辟": 2832, "藤": 2833, "鉉": 2834, "抑": 2835, "慷": 2836, "漬": 2837, "籽": 2838, "閘": 2839, "泌": 2840, "醃": 2841, "焙": 2842, "％": 2843, "采": 2844, "窟": 2845, "吶": 2846, "灸": 2847, "訕": 2848, "薩": 2849, "薰": 2850, "奄": 2851, "耽": 2852, "啃": 2853, "禿": 2854, "庶": 2855, "霉": 2856, "詭": 2857, "扔": 2858, "杞": 2859, "粥": 2860, "咕": 2861, "孑": 2862, "孓": 2863, "弓": 2864, "脯": 2865, "瓠": 2866, "憨": 2867, "卓": 2868, "婉": 2869, "蠟": 2870, "肆": 2871, "橘": 2872, "涂": 2873, "濾": 2874, "卿": 2875, "緬": 2876, "汰": 2877, "糰": 2878, "膨": 2879, "儒": 2880, "苑": 2881, "墩": 2882, "岳": 2883, "曙": 2884, "悍": 2885, "嘔": 2886, "魷": 2887, "殯": 2888, "曼": 2889, "澈": 2890, "蔘": 2891, "焰": 2892, "饗": 2893, "鷥": 2894, "渾": 2895, "臺": 2896, "摻": 2897, "槌": 2898, "棺": 2899, "撇": 2900, "匆": 2901, "囝": 2902, "菩": 2903, "儉": 2904, "恍": 2905, "汐": 2906, "刁": 2907, "姻": 2908, "漥": 2909, "迢": 2910, "寂": 2911, "埃": 2912, "笛": 2913, "灶": 2914, "枸": 2915, "萎": 2916, "嚮": 2917, "浬": 2918, "籬": 2919, "肘": 2920, "劈": 2921, "徙": 2922, "庵": 2923, "馴": 2924, "姦": 2925, "攙": 2926, "譬": 2927, "緯": 2928, "佐": 2929, "瑕": 2930, "疵": 2931, "云": 2932, "膝": 2933, "乃": 2934, "郊": 2935, "禧": 2936, "跆": 2937, "鵟": 2938, "鉅": 2939, "禦": 2940, "鰨": 2941, "邵": 2942, "賑": 2943, "踹": 2944, "沛": 2945, "揪": 2946, "忡": 2947, "苔": 2948, "喻": 2949, "恭": 2950, "槓": 2951, "豹": 2952, "墳": 2953, "徘": 2954, "徊": 2955, "愧": 2956, "忿": 2957, "鯛": 2958, "勳": 2959, "馮": 2960, "竅": 2961, "匹": 2962, "襯": 2963, "螫": 2964, "膳": 2965, "咪": 2966, "倖": 2967, "訣": 2968, "梧": 2969, "軸": 2970, "鱸": 2971, "鹼": 2972, "框": 2973, "纍": 2974, "笠": 2975, "鋏": 2976, "塱": 2977, "腥": 2978, "嘖": 2979, "咾": 2980, "衍": 2981, "癢": 2982, "茸": 2983, "掠": 2984, "曹": 2985, "婿": 2986, "靂": 2987, "丐": 2988, "鄧": 2989, "豫": 2990, "盞": 2991, "杰": 2992, "嬌": 2993, "悟": 2994, "顱": 2995, "瞪": 2996, "萊": 2997, "賀": 2998, "洶": 2999, "‧": 3000, "弔": 3001, "睞": 3002, "猖": 3003, "啞": 3004, "軀": 3005, "佯": 3006, "啥": 3007, "荖": 3008, "遂": 3009, "杆": 3010, "奕": 3011, "輒": 3012, "矗": 3013, "搗": 3014, "彭": 3015, "咱": 3016, "莖": 3017, "銓": 3018, "嚎": 3019, "淘": 3020, "鯧": 3021, "狸": 3022, "呵": 3023, "餃": 3024, "矩": 3025, "哮": 3026, "蚯": 3027, "蚓": 3028, "絆": 3029, "畔": 3030, "孵": 3031, "閔": 3032, "檸": 3033, "檬": 3034, "繽": 3035, "瓣": 3036, "陋": 3037, "桔": 3038, "貳": 3039, "蜥": 3040, "蜴": 3041, "擂": 3042, "娼": 3043, "冉": 3044, "頌": 3045, "獮": 3046, "鼬": 3047, "獾": 3048, "癬": 3049, "檻": 3050, "瑜": 3051, "廿": 3052, "抨": 3053, "巫": 3054, "剎": 3055, "渦": 3056, "甦": 3057, "晏": 3058, "坎": 3059, "狡": 3060, "燦": 3061, "奠": 3062, "銜": 3063, "髓": 3064, "奢": 3065, "～": 3066, "粹": 3067, "輿": 3068, "筷": 3069, "疆": 3070, "磅": 3071, "犁": 3072, "挾": 3073, "恤": 3074, "炫": 3075, "懇": 3076, "虔": 3077, "侶": 3078, "炙": 3079, "瞎": 3080, "蹄": 3081, "驟": 3082, "缸": 3083, "喉": 3084, "噬": 3085, "囊": 3086, "醞": 3087, "瘀": 3088, "遁": 3089, "唆": 3090, "嗜": 3091, "蹺": 3092, "飪": 3093, "町": 3094, "溯": 3095, "霄": 3096, "趾": 3097, "瀑": 3098, "袍": 3099, "咆": 3100, "噓": 3101, "懺": 3102, "逞": 3103, "丑": 3104, "咽": 3105, "哨": 3106, "泊": 3107, "凰": 3108, "弦": 3109, "硫": 3110, "陀": 3111, "蒡": 3112, "傢": 3113, "壺": 3114, "咐": 3115, "鋤": 3116, "馳": 3117, "麩": 3118, "哺": 3119, "逵": 3120, "姆": 3121, "◎": 3122, "爲": 3123, "寡": 3124, "紳": 3125, "唾": 3126, "簿": 3127, "蹧": 3128, "鈞": 3129, "趙": 3130, "J": 3131, "謙": 3132, "賦": 3133, "姬": 3134, "窒": 3135, "譚": 3136, "啼": 3137, "捆": 3138, "赫": 3139, "眉": 3140, "刈": 3141, "宕": 3142, "唁": 3143, "淒": 3144, "屐": 3145, "臘": 3146, "韌": 3147, "鯊": 3148, "綻": 3149, "嗓": 3150, "諱": 3151, "冥": 3152, "偕": 3153, "綽": 3154, "魁": 3155, "嘩": 3156, "諮": 3157, "搏": 3158, "銹": 3159, "瑋": 3160, "孳": 3161, "榖": 3162, "貶": 3163, "沐": 3164, "匣": 3165, "揉": 3166, "咎": 3167, "濬": 3168, "麴": 3169, "渠": 3170, "怵": 3171, "牟": 3172, "鋅": 3173, "鯉": 3174, "秉": 3175, "嗣": 3176, "涔": 3177, "邪": 3178, "拗": 3179, "冕": 3180, "祟": 3181, "鍰": 3182, "澀": 3183, "睬": 3184, "忱": 3185, "欉": 3186, "昊": 3187, "縉": 3188, "鶴": 3189, "萣": 3190, "渥": 3191, "畚": 3192, "箕": 3193, "嚼": 3194, "沃": 3195, "癲": 3196, "帖": 3197, "笭": 3198, "搓": 3199, "蟑": 3200, "螂": 3201, "扳": 3202, "釁": 3203, "譁": 3204, "迄": 3205, "峻": 3206, "耆": 3207, "覃": 3208, "磯": 3209, "倡": 3210, "飢": 3211, "骯": 3212, "腕": 3213, "謎": 3214, "繹": 3215, "囉": 3216, "妓": 3217, "証": 3218, "侷": 3219, "郡": 3220, "墟": 3221, "叉": 3222, "嚏": 3223, "醋": 3224, "姪": 3225, "裔": 3226, "甕": 3227, "殷": 3228, "尷": 3229, "尬": 3230, "惟": 3231, "晰": 3232, "彬": 3233, "渙": 3234, "塢": 3235, "崛": 3236, "挪": 3237, "癡": 3238, "怯": 3239, "搐": 3240, "矢": 3241, "矇": 3242, "撻": 3243, "窘": 3244, "壢": 3245, "癒": 3246, "犒": 3247, "琅": 3248, "慚": 3249, "睫": 3250, "氫": 3251, "嗅": 3252, "餚": 3253, "肋": 3254, "鱺": 3255, "悽": 3256, "疤": 3257, "穫": 3258, "鯰": 3259, "哼": 3260, "瀰": 3261, "綴": 3262, "頰": 3263, "噱": 3264, "駿": 3265, "摀": 3266, "陡": 3267, "唇": 3268, "漳": 3269, "藻": 3270, "墅": 3271, "勻": 3272, "絮": 3273, "吩": 3274, "癇": 3275, "粄": 3276, "髦": 3277, "荼": 3278, "鯖": 3279, "愣": 3280, "栫": 3281, "楓": 3282, "櫥": 3283, "閩": 3284, "惰": 3285, "吱": 3286, "曜": 3287, "磬": 3288, "懦": 3289, "͘": 3290, "呀": 3291, "躂": 3292, "渺": 3293, "譙": 3294, "卅": 3295, "踝": 3296, "憊": 3297, "璟": 3298, "暨": 3299, "桓": 3300, "嚀": 3301, "俠": 3302, "綵": 3303, "噩": 3304, "坷": 3305, "僕": 3306, "凋": 3307, "吝": 3308, "翱": 3309, "拄": 3310, "稠": 3311, "抉": 3312, "拇": 3313, "遼": 3314, "瞰": 3315, "脾": 3316, "廬": 3317, "鍛": 3318, "炬": 3319, "亢": 3320, "麝": 3321, "冀": 3322, "胺": 3323, "堃": 3324, "誣": 3325, "汞": 3326, "擒": 3327, "悚": 3328, "枕": 3329, "厥": 3330, "卹": 3331, "嚨": 3332, "慫": 3333, "恿": 3334, "陵": 3335, "湍": 3336, "葛": 3337, "鱗": 3338, "瀆": 3339, "啕": 3340, "遏": 3341, "譏": 3342, "斧": 3343, "刪": 3344, "瘧": 3345, "怠": 3346, "瀛": 3347, "殆": 3348, "蛻": 3349, "狐": 3350, "卉": 3351, "枚": 3352, "吋": 3353, "柺": 3354, "苛": 3355, "氓": 3356, "夷": 3357, "剉": 3358, "盎": 3359, "迪": 3360, "唉": 3361, "哇": 3362, "綑": 3363, "鈣": 3364, "鎂": 3365, "撬": 3366, "哽": 3367, "綢": 3368, "鬚": 3369, "唬": 3370, "賒": 3371, "坊": 3372, "馗": 3373, "簍": 3374, "啪": 3375, "伶": 3376, "堰": 3377, "禪": 3378, "浚": 3379, "滄": 3380, "剃": 3381, "堀": 3382, "壩": 3383, "嫂": 3384, "伕": 3385, "揶": 3386, "揄": 3387, "焊": 3388, "于": 3389, "焜": 3390, "瞌": 3391, "佣": 3392, "摳": 3393, "洄": 3394, "頹": 3395, "粕": 3396, "噎": 3397, "佇": 3398, "靖": 3399, "恂": 3400, "啜": 3401, "煽": 3402, "仕": 3403, "ⁿ": 3404, "彙": 3405, "̍": 3406, "バ": 3407, "イ": 3408, "ク": 3409, "毋": 3410, "踵": 3411, "壙": 3412, "暇": 3413, "聳": 3414, "逕": 3415, "桅": 3416, "雯": 3417, "槳": 3418, "璋": 3419, "隘": 3420, "厄": 3421, "詫": 3422, "虞": 3423, "瑛": 3424, "娟": 3425, "籟": 3426, "嗇": 3427, "寇": 3428, "拯": 3429, "婪": 3430, "妖": 3431, "崖": 3432, "伉": 3433, "儷": 3434, "詼": 3435, "鈺": 3436, "妃": 3437, "磐": 3438, "嘶": 3439, "壘": 3440, "泮": 3441, "諭": 3442, "濘": 3443, "芙": 3444, "睽": 3445, "馭": 3446, "貯": 3447, "糗": 3448, "氰": 3449, "襪": 3450, "酗": 3451, "峙": 3452, "揍": 3453, "巿": 3454, "燄": 3455, "濛": 3456, "芎": 3457, "詛": 3458, "惕": 3459, "吻": 3460, "莽": 3461, "駭": 3462, "炔": 3463, "剿": 3464, "烯": 3465, "疚": 3466, "晟": 3467, "氾": 3468, "伺": 3469, "攸": 3470, "暮": 3471, "潟": 3472, "菅": 3473, "謗": 3474, "寞": 3475, "俸": 3476, "斬": 3477, "敞": 3478, "鬍": 3479, "痲": 3480, "卯": 3481, "骰": 3482, "僥": 3483, "苞": 3484, "獗": 3485, "摑": 3486, "剋": 3487, "繭": 3488, "瑤": 3489, "煒": 3490, "袱": 3491, "豚": 3492, "淌": 3493, "兢": 3494, "僧": 3495, "痞": 3496, "屹": 3497, "宙": 3498, "哉": 3499, "妞": 3500, "旻": 3501, "砧": 3502, "屜": 3503, "簷": 3504, "邸": 3505, "頑": 3506, "枇": 3507, "杷": 3508, "跛": 3509, "壕": 3510, "餌": 3511, "痠": 3512, "燻": 3513, "逍": 3514, "眺": 3515, "芥": 3516, "峭": 3517, "腮": 3518, "陲": 3519, "犀": 3520, "蝨": 3521, "豉": 3522, "涕": 3523, "惚": 3524, "漯": 3525, "蝸": 3526, "凳": 3527, "閏": 3528, "檜": 3529, "佃": 3530, "鰲": 3531, "憋": 3532, "醮": 3533, "竣": 3534, "媚": 3535, "睿": 3536, "吠": 3537, "嘟": 3538, "瑄": 3539, "梆": 3540, "徬": 3541, "徨": 3542, "畦": 3543, "穢": 3544, "茅": 3545, "萱": 3546, "倚": 3547, "柄": 3548, "蹦": 3549, "嚥": 3550, "礫": 3551, "羌": 3552, "匡": 3553, "à": 3554, "ā": 3555, "ō": 3556, "â": 3557, "̄": 3558, "喬": 3559, "箇": 3560, "眈": 3561, "杭": 3562, "吁": 3563, "莎": 3564, "喋": 3565, "": 3566, "袂": 3567, "璁": 3568, "剽": 3569, "＜": 3570, "＞": 3571, "堦": 3572, "穌": 3573, "恕": 3574, "暉": 3575, "萌": 3576, "侃": 3577, "－": 3578, "棘": 3579, "浙": 3580, "骷": 3581, "髏": 3582, "坌": 3583, "峒": 3584, "搧": 3585, "熒": 3586, "稟": 3587, "葯": 3588, "詡": 3589, "聾": 3590, "疹": 3591, "畝": 3592, "俯": 3593, "摯": 3594, "篤": 3595, "鑫": 3596, "窺": 3597, "膾": 3598, "袁": 3599, "杓": 3600, "戕": 3601, "怡": 3602, "酯": 3603, "褪": 3604, "腋": 3605, "鬃": 3606, "瘡": 3607, "嬉": 3608, "眩": 3609, "臆": 3610, "鴛": 3611, "鴦": 3612, "猥": 3613, "褻": 3614, "懊": 3615, "泓": 3616, "烙": 3617, "囑": 3618, "撩": 3619, "幌": 3620, "阪": 3621, "俏": 3622, "晝": 3623, "祂": 3624, "餞": 3625, "淆": 3626, "粟": 3627, "爍": 3628, "磷": 3629, "宥": 3630, "鑿": 3631, "愕": 3632, "匱": 3633, "汪": 3634, "宦": 3635, "誹": 3636, "瞄": 3637, "姜": 3638, "儼": 3639, "箝": 3640, "惺": 3641, "遛": 3642, "龔": 3643, "朽": 3644, "剁": 3645, "戈": 3646, "Z": 3647, "萃": 3648, "斂": 3649, "芡": 3650, "棧": 3651, "暄": 3652, "錙": 3653, "銖": 3654, "亟": 3655, "迸": 3656, "鰭": 3657, "剔": 3658, "撓": 3659, "錐": 3660, "弛": 3661, "茁": 3662, "頤": 3663, "莢": 3664, "岌": 3665, "轍": 3666, "垵": 3667, "袈": 3668, "裟": 3669, "摟": 3670, "浹": 3671, "漩": 3672, "稈": 3673, "黯": 3674, "惘": 3675, "偎": 3676, "埂": 3677, "詬": 3678, "梢": 3679, "雉": 3680, "跤": 3681, "芸": 3682, "孀": 3683, "稼": 3684, "蘑": 3685, "膊": 3686, "御": 3687, "拭": 3688, "忞": 3689, "鳩": 3690, "曦": 3691, "簸": 3692, "鍥": 3693, "蜈": 3694, "蚣": 3695, "嚷": 3696, "蔑": 3697, "痢": 3698, "芍": 3699, "癩": 3700, "罡": 3701, "妤": 3702, "舀": 3703, "篡": 3704, "軒": 3705, "篷": 3706, "颳": 3707, "亨": 3708, "憫": 3709, "遑": 3710, "遜": 3711, "痘": 3712, "脣": 3713, "汲": 3714, "j": 3715, "矣": 3716, "閹": 3717, "没": 3718, "苟": 3719, "晦": 3720, "乍": 3721, "愿": 3722, "恣": 3723, "○": 3724, "咧": 3725, "塚": 3726, "贅": 3727, "瑣": 3728, "瞻": 3729, "喃": 3730, "騁": 3731, "焉": 3732, "褫": 3733, "楹": 3734, "餬": 3735, "碉": 3736, "晤": 3737, "闡": 3738, "咄": 3739, "芮": 3740, "蔚": 3741, "瞑": 3742, "埠": 3743, "﹔": 3744, "祿": 3745, "倭": 3746, "袒": 3747, "氦": 3748, "懈": 3749, "岱": 3750, "謄": 3751, "掮": 3752, "炊": 3753, "鍘": 3754, "嚕": 3755, "穆": 3756, "臀": 3757, "齋": 3758, "鮑": 3759, "鎘": 3760, "赦": 3761, "恬": 3762, "耿": 3763, "鎊": 3764, "箔": 3765, "揣": 3766, "霓": 3767, "暱": 3768, "飭": 3769, "憩": 3770, "倘": 3771, "'": 3772, "饞": 3773, "帑": 3774, "鉀": 3775, "臍": 3776, "淳": 3777, "咳": 3778, "嗽": 3779, "疙": 3780, "瘩": 3781, "豋": 3782, "鈕": 3783, "膛": 3784, "蜻": 3785, "蜓": 3786, "苯": 3787, "缽": 3788, "魘": 3789, "湮": 3790, "ㄚ": 3791, "燿": 3792, "弒": 3793, "掐": 3794, "葫": 3795, "几": 3796, "庸": 3797, "慟": 3798, "艋": 3799, "舺": 3800, "賂": 3801, "煤": 3802, "拱": 3803, "蹊": 3804, "恙": 3805, "淩": 3806, "媺": 3807, "燼": 3808, "燬": 3809, "肛": 3810, "梟": 3811, "捻": 3812, "輟": 3813, "賃": 3814, "矽": 3815, "孽": 3816, "筱": 3817, "攢": 3818, "斐": 3819, "圃": 3820, "鳶": 3821, "嵙": 3822, "饒": 3823, "滌": 3824, "惋": 3825, "鏘": 3826, "啷": 3827, "鯨": 3828, "涸": 3829, "槁": 3830, "燴": 3831, "蠕": 3832, "弭": 3833, "鴕": 3834, "瀚": 3835, "猾": 3836, "閥": 3837, "拎": 3838, "榴": 3839, "鑄": 3840, "盥": 3841, "睦": 3842, "莿": 3843, "貍": 3844, "饑": 3845, "乒": 3846, "乓": 3847, "闔": 3848, "閡": 3849, "凜": 3850, "醺": 3851, "腱": 3852, "玳": 3853, "瑁": 3854, "橢": 3855, "吭": 3856, "渝": 3857, "囪": 3858, "鸛": 3859, "跋": 3860, "柬": 3861, "寨": 3862, "嘸": 3863, "杏": 3864, "晾": 3865, "窪": 3866, "涎": 3867, "莞": 3868, "糠": 3869, "錚": 3870, "朔": 3871, "倦": 3872, "悻": 3873, "刃": 3874, "胱": 3875, "舢": 3876, "舨": 3877, "錠": 3878, "琦": 3879, "玟": 3880, "吏": 3881, "喳": 3882, "娓": 3883, "狽": 3884, "藐": 3885, "鶩": 3886, "芯": 3887, "餒": 3888, "蕎": 3889, "狩": 3890, "簧": 3891, "駝": 3892, "烊": 3893, "啄": 3894, "璧": 3895, "撂": 3896, "倪": 3897, "餾": 3898, "紜": 3899, "琢": 3900, "錘": 3901, "棠": 3902, "雁": 3903, "涮": 3904, "苓": 3905, "傀": 3906, "儡": 3907, "喆": 3908, "孜": 3909, "竺": 3910, "斛": 3911, "笙": 3912, "蔦": 3913, "咚": 3914, "鐮": 3915, "羔": 3916, "胚": 3917, "歆": 3918, "靡": 3919, "聒": 3920, "篦": 3921, "榫": 3922, "垛": 3923, "櫟": 3924, "擻": 3925, "躡": 3926, "抒": 3927, "蜿": 3928, "蜒": 3929, "棕": 3930, "翟": 3931, "鈉": 3932, "嗡": 3933, "鸚": 3934, "韭": 3935, "轆": 3936, "漓": 3937, "骸": 3938, "窿": 3939, "彆": 3940, "皺": 3941, "壅": 3942, "砰": 3943, "栓": 3944, "搥": 3945, "鈑": 3946, "箏": 3947, "誨": 3948, "諉": 3949, "蠹": 3950, "嗦": 3951, "遽": 3952, "咸": 3953, "蓁": 3954, "姣": 3955, "歎": 3956, "唧": 3957, "慼": 3958, "眨": 3959, "嬷": 3960, "鈍": 3961, "潦": 3962, "狕": 3963, "縈": 3964, "枷": 3965, "曖": 3966, "抝": 3967, "踽": 3968, "拂": 3969, "潺": 3970, "繆": 3971, "膺": 3972, "惆": 3973, "悵": 3974, "屌": 3975, "吆": 3976, "兀": 3977, "蕪": 3978, "罔": 3979, "叨": 3980, "渲": 3981, "蓼": 3982, "澹": 3983, "湠": 3984, "暝": 3985, "癖": 3986, "稜": 3987, "庒": 3988, "ì": 3989, "銫": 3990, "穡": 3991, "爹": 3992, "匍": 3993, "匐": 3994, "榆": 3995, "蒞": 3996, "鎩": 3997, "翰": 3998, "訃": 3999, "苺": 4000, "豁": 4001, "榻": 4002, "鎌": 4003, "箋": 4004, "玿": 4005, "捅": 4006, "雋": 4007, "鷲": 4008, "詰": 4009, "侈": 4010, "獷": 4011, "蒲": 4012, "吟": 4013, "骼": 4014, "棣": 4015, "q": 4016, "紕": 4017, "釉": 4018, "蕁": 4019, "尪": 4020, "熾": 4021, "舵": 4022, "俟": 4023, "爵": 4024, "揖": 4025, "佟": 4026, "鴞": 4027, "侑": 4028, "奚": 4029, "陝": 4030, "繚": 4031, "壼": 4032, "竇": 4033, "瑟": 4034, "楞": 4035, "嘹": 4036, "堯": 4037, "眸": 4038, "疥": 4039, "叩": 4040, "妾": 4041, "殞": 4042, "簇": 4043, "飴": 4044, "貽": 4045, "寀": 4046, "臻": 4047, "蚱": 4048, "蜢": 4049, "鐺": 4050, "磋": 4051, "掖": 4052, "蟬": 4053, "綬": 4054, "瑲": 4055, "晒": 4056, "鋌": 4057, "媲": 4058, "鰹": 4059, "鰡": 4060, "踮": 4061, "釧": 4062, "紂": 4063, "扈": 4064, "艾": 4065, "孅": 4066, "甄": 4067, "摃": 4068, "忪": 4069, "熔": 4070, "拷": 4071, "蒟": 4072, "蒻": 4073, "薏": 4074, "珈": 4075, "嫖": 4076, "瞳": 4077, "碁": 4078, "滂": 4079, "沱": 4080, "淖": 4081, "•": 4082, "湳": 4083, "毓": 4084, "瑾": 4085, "鍍": 4086, "嗚": 4087, "酌": 4088, "閑": 4089, "斡": 4090, "遴": 4091, "坵": 4092, "瀟": 4093, "蕊": 4094, "澧": 4095, "泯": 4096, "鉻": 4097, "侖": 4098, "殤": 4099, "蛀": 4100, "粘": 4101, "奐": 4102, "咋": 4103, "岔": 4104, "闌": 4105, "濺": 4106, "嶸": 4107, "湛": 4108, "佰": 4109, "鑷": 4110, "霾": 4111, "糬": 4112, "茵": 4113, "蛹": 4114, "侍": 4115, "獠": 4116, "廍": 4117, "沅": 4118, "鵲": 4119, "姵": 4120, "薈": 4121, "珮": 4122, "｢": 4123, "｣": 4124, "鑲": 4125, "鏨": 4126, "【": 4127, "】": 4128, "辮": 4129, "蕾": 4130, "砌": 4131, "痧": 4132, "賈": 4133, "蒝": 4134, "褐": 4135, "麒": 4136, "湘": 4137, "稔": 4138, "簑": 4139, "韻": 4140, "鯤": 4141, "鯓": 4142, "孺": 4143, "巔": 4144, "藹": 4145, "鯽": 4146, "楔": 4147, "蠶": 4148, "拙": 4149, "愜": 4150, "痱": 4151, "嶽": 4152, "焢": 4153, "翳": 4154, "蜷": 4155, "鉑": 4156, "襬": 4157, "釦": 4158, "嶄": 4159, "雌": 4160, "孢": 4161, "蚜": 4162, "拮": 4163, "据": 4164, "紉": 4165, "螯": 4166, "峯": 4167, "垢": 4168, "豺": 4169, "輓": 4170, "櫚": 4171, "鵑": 4172, "靚": 4173, "筠": 4174, "檀": 4175, "硃": 4176, "扼": 4177, "呎": 4178, "琄": 4179, "舷": 4180, "瞠": 4181, "噌": 4182, "沮": 4183, "殭": 4184, "菠": 4185, "黝": 4186, "蚌": 4187, "霰": 4188, "橙": 4189, "茴": 4190, "瘍": 4191, "蚤": 4192, "痊": 4193, "膿": 4194, "邋": 4195, "遢": 4196, "餉": 4197, "慿": 4198, "汶": 4199, "箴": 4200, "麾": 4201, "瘠": 4202, "櫛": 4203, "滬": 4204, "靨": 4205, "炷": 4206, "梳": 4207, "酚": 4208, "硯": 4209, "俳": 4210, "嗝": 4211, "弗": 4212, "磕": 4213, "漣": 4214, "傭": 4215, "沽": 4216, "噤": 4217, "緘": 4218, "蟄": 4219, "騖": 4220, "竽": 4221, "碓": 4222, "詎": 4223, "咨": 4224, "貉": 4225, "籮": 4226, "筐": 4227, "潸": 4228, "掺": 4229, "瘟": 4230, "蹶": 4231, "捫": 4232, "ù": 4233, "û": 4234, "鹸": 4235, "ò": 4236, "噗": 4237, "嗤": 4238, "蹂": 4239, "躪": 4240, "徜": 4241, "徉": 4242, "–": 4243, "賁": 4244, "毽": 4245, "蔴": 4246, "儆": 4247, "簣": 4248, "癆": 4249, "遐": 4250, "瞥": 4251, "哦": 4252, "銍": 4253, "筵": 4254, "揆": 4255, "鑒": 4256, "愫": 4257, "扉": 4258, "忤": 4259, "嘿": 4260, "掰": 4261, "帷": 4262, "厘": 4263, "靦": 4264, "腆": 4265, "鞘": 4266, "瞇": 4267, "劊": 4268, "á": 4269, "玷": 4270, "葦": 4271, "曳": 4272, "榷": 4273, "╱": 4274, "褒": 4275, "殮": 4276, "矯": 4277, "禾": 4278, "謳": 4279, "撮": 4280, "祉": 4281, "瞿": 4282, "軔": 4283, "喲": 4284, "擷": 4285, "憎": 4286, "鎔": 4287, "慄": 4288, "樞": 4289, "櫫": 4290, "甬": 4291, "扞": 4292, "é": 4293, "襟": 4294, "叙": 4295, "吮": 4296, "荐": 4297, "痍": 4298, "匏": 4299, "柢": 4300, "戮": 4301, "嘮": 4302, "唏": 4303, "癥": 4304, "豢": 4305, "効": 4306, "丕": 4307, "篠": 4308, "諦": 4309, "扒": 4310, "隴": 4311, "牴": 4312, "懿": 4313, "淬": 4314, "恁": 4315, "蘊": 4316, "嬗": 4317, "糜": 4318, "霑": 4319, "吾": 4320, "î": 4321, "ū": 4322, "ô": 4323, "劵": 4324, "緋": 4325, "湄": 4326, "裳": 4327, "õ": 4328, "ń": 4329, "ú": 4330, "囿": 4331, "鞍": 4332, "猿": 4333, "捶": 4334, "睪": 4335, "痹": 4336, "酣": 4337, "訐": 4338, "掄": 4339, "烽": 4340, "楝": 4341, "欒": 4342, "瀨": 4343, "嗨": 4344, "俎": 4345, "恃": 4346, "罟": 4347, "眞": 4348, "嗯": 4349, "衊": 4350, "俑": 4351, "芹": 4352, "浦": 4353, "嗑": 4354, "坨": 4355, "懟": 4356, "垠": 4357, "胳": 4358, "胼": 4359, "胝": 4360, "拈": 4361, "歭": 4362}